[
  {
    "id": "pgi.const.industry",
    "type": "FACTORY",
    "max_level": 100,
    "construction_inputs": [
      {
        "resource": "CONSTRUCTION",
        "quantity": 330750,
        "max_velocity": 8268.75
      },
      {
        "resource": "MACHINERY",
        "quantity": 3675,
        "max_velocity": 91.875
      },
      {
        "resource": "COMPUTER",
        "quantity": 13781.25,
        "max_velocity": 344.53125
      }
    ],
    "stages": [
      {
        "index": 1,
        "duration": 1,
        "stage_inputs": [],
        "labor": [
          {
            "resource": "PROFESSIONAL",
            "max_velocity": 6,
            "weight_efficiency": 0,
            "weight_quality": 0
          },
          {
            "resource": "WORKER",
            "max_velocity": 237,
            "weight_efficiency": 0,
            "weight_quality": 0
          }
        ],
        "operations": [
          {
            "resource": "COMPUTER_SERVICE",
            "max_velocity": 1,
            "weight_efficiency": 0,
            "weight_quality": 0
          },
          {
            "resource": "LEGAL_SERVICE",
            "max_velocity": 0.25,
            "weight_efficiency": 0,
            "weight_quality": 0
          }
        ],
        "inputs": [
          {
            "resource": "ORE",
            "max_velocity": 300,
            "weight_efficiency": 0,
            "weight_quality": 0
          },
          {
            "resource": "METAL",
            "max_velocity": 62,
            "weight_efficiency": 0,
            "weight_quality": 0
          },
          {
            "resource": "CHEMICAL",
            "max_velocity": 62,
            "weight_efficiency": 0,
            "weight_quality": 0
          },
          {
            "resource": "TIMBER",
            "max_velocity": 200,
            "weight_efficiency": 0,
            "weight_quality": 0
          }
        ],
        "outputs": [
          {
            "resource": "CONSTRUCTION",
            "max_velocity": 50,
            "weight_efficiency": 0,
            "weight_quality": 0
          }
        ]
      }
    ]
  }
]
