[
  {
    "cost": 73500000,
    "construction": {
      "duration": 40,
      "cost": [
        {
          "resource": "CONSTRUCTION",
          "max": 45
        },
        {
          "resource": "MACHINERY",
          "max": 40
        },
        {
          "resource": "COMPUTER",
          "max": 15
        }
      ]
    },
    "required_inputs": [
      {
        "resource": "ORE",
        "max": 300
      },
      {
        "resource": "METAL",
        "max": 62
      },
      {
        "resource": "CHEMICAL",
        "max": 62
      },
      {
        "resource": "TIMBER",
        "max": 200
      },
      {
        "resource": "PROFESSIONAL",
        "max": 6
      },
      {
        "resource": "WORKER",
        "max": 237
      }
    ],
    "optional_inputs": [
      {
        "resource": "COMPUTER_SERVICES",
        "max": 1
      },
      {
        "resource": "LEGAL_SERVICES",
        "max": 0.25
      }
    ],
    "outputs": [
      {
        "resource": "CONSTRUCTION",
        "max": 50
      }
    ],
    "id": "pgi.const.industry",
    "type": "INDUSTRY"
  }
]
