[
  {
    "id": "dis.metal.industry",
    "type": "FACTORY",
    "maxLevel": 100,
    "constructionInputs": [
      {
        "resourceId": "CONSTRUCTION",
        "quantity": 134400,
        "maxVelocity": 2986.6666666666665
      },
      {
        "resourceId": "MACHINERY",
        "quantity": 2100,
        "maxVelocity": 46.666666666666664
      },
      {
        "resourceId": "COMPUTER",
        "quantity": 4200,
        "maxVelocity": 93.33333333333333
      }
    ],
    "labor": [
      {
        "resourceId": "PROFESSIONAL",
        "maxVelocity": 2,
        "weightEfficiency": 0,
        "weightQuality": 0
      },
      {
        "resourceId": "WORKER",
        "maxVelocity": 120,
        "weightEfficiency": 0,
        "weightQuality": 0
      }
    ],
    "operations": [
      {
        "resourceId": "COMPUTER_SERVICE",
        "maxVelocity": 0.2,
        "weightEfficiency": 0,
        "weightQuality": 0
      },
      {
        "resourceId": "LEGAL_SERVICE",
        "maxVelocity": 0.12,
        "weightEfficiency": 0,
        "weightQuality": 0
      }
    ],
    "inputs": [
      {
        "resourceId": "ORE",
        "maxVelocity": 288,
        "weightEfficiency": 0,
        "weightQuality": 0
      },
      {
        "resourceId": "CHEMICAL",
        "maxVelocity": 21,
        "weightEfficiency": 0,
        "weightQuality": 0
      }
    ],
    "outputs": [
      {
        "resourceId": "METAL",
        "maxVelocity": 144,
        "weightEfficiency": 0,
        "weightQuality": 0
      }
    ]
  },
  {
    "id": "dis.metal.industry.small",
    "type": "FACTORY",
    "maxLevel": 100,
    "constructionInputs": [
      {
        "resourceId": "CONSTRUCTION",
        "quantity": 32000,
        "maxVelocity": 711.1111111111111
      },
      {
        "resourceId": "MACHINERY",
        "quantity": 500,
        "maxVelocity": 11.11111111111111
      },
      {
        "resourceId": "COMPUTER",
        "quantity": 1000,
        "maxVelocity": 22.22222222222222
      }
    ],
    "labor": [
      {
        "resourceId": "PROFESSIONAL",
        "maxVelocity": 1,
        "weightEfficiency": 0,
        "weightQuality": 0
      },
      {
        "resourceId": "WORKER",
        "maxVelocity": 70,
        "weightEfficiency": 0,
        "weightQuality": 0
      }
    ],
    "operations": [
      {
        "resourceId": "COMPUTER_SERVICE",
        "maxVelocity": 0.08,
        "weightEfficiency": 0,
        "weightQuality": 0
      },
      {
        "resourceId": "LEGAL_SERVICE",
        "maxVelocity": 0.04,
        "weightEfficiency": 0,
        "weightQuality": 0
      }
    ],
    "inputs": [
      {
        "resourceId": "ORE",
        "maxVelocity": 96,
        "weightEfficiency": 0,
        "weightQuality": 0
      },
      {
        "resourceId": "CHEMICAL",
        "maxVelocity": 7,
        "weightEfficiency": 0,
        "weightQuality": 0
      }
    ],
    "outputs": [
      {
        "resourceId": "METAL",
        "maxVelocity": 48,
        "weightEfficiency": 0,
        "weightQuality": 0
      }
    ]
  }
]
